README.md
setup.cfg
setup.py
bin/kubestash
kubestash/__init__.py
kubestash/__main__.py
kubestash.egg-info/PKG-INFO
kubestash.egg-info/SOURCES.txt
kubestash.egg-info/dependency_links.txt
kubestash.egg-info/requires.txt
kubestash.egg-info/top_level.txt