Metadata-Version: 1.0
Name: kubestash
Version: 1.0.0
Summary: Push your Credstash secrets to Kubernetes.
Home-page: https://github.com/af-inet/kubestash
Author: David Hargat
Author-email: davidmhargat@gmail.com
License: MIT
Keywords: k8s,kubernetes,credstash
Platform: UNKNOWN
